logger/__init__.py
logger/logger.py
logger/logger_exception.py
logger/logger_interface.py
plogger/__init__.py
plogger/logger.py
plogger/logger_exception.py
plogger/logger_interface.py
plogger_develhoper-0.1.2.dist-info/LICENSE
plogger_develhoper-0.1.2.dist-info/METADATA
plogger_develhoper-0.1.2.dist-info/WHEEL
plogger_develhoper-0.1.2.dist-info/top_level.txt
plogger_develhoper-0.1.2.dist-info/RECORD
