Metadata-Version: 2.1
Name: plogger-develhoper
Version: 0.1.2
Summary: Log like a pro (: kidding :)
Home-page: https://github.com/develhopper/plogger
Author: develhoper
Author-email: develhoper.0@gmail.com
License: UNKNOWN
Platform: UNKNOWN
Classifier: Programming Language :: Python :: 3
Classifier: License :: OSI Approved :: GNU General Public License v3 (GPLv3)
Classifier: Operating System :: OS Independent
